drdigit/__init__.py
drdigit/digit_correlations.py
drdigit/digit_distribution_charts.py
drdigit/digit_entropy_distribution.py
drdigit/digit_filtering.py
drdigit/entropy_plots.py
drdigit/fingerprint_plots.py
drdigit/scoring.py
drdigit/twin_digits.py
tests/__init__.py
tests/test_digit_correlations.py
tests/test_digit_entropy.py
tests/test_digit_filtering.py
tests/test_twin_digits.py
drdigit_brezniczky-0.0.17.dist-info/LICENSE
drdigit_brezniczky-0.0.17.dist-info/METADATA
drdigit_brezniczky-0.0.17.dist-info/WHEEL
drdigit_brezniczky-0.0.17.dist-info/top_level.txt
drdigit_brezniczky-0.0.17.dist-info/RECORD
