Metadata-Version: 2.1
Name: drdigit-brezniczky
Version: 0.0.17
Summary: A digit doctoring detection package
Home-page: https://github.com/brezniczky/drdigit
Author: Janos Brezniczky
Author-email: brezniczky@gmail.com
License: UNKNOWN
Platform: UNKNOWN
Classifier: Programming Language :: Python :: 3
Classifier: License :: OSI Approved :: GNU General Public License v2 or later (GPLv2+)
Classifier: Operating System :: OS Independent
Classifier: Development Status :: 1 - Planning 
Classifier: Topic :: Scientific/Engineering
Requires-Dist: attrs (==19.1.0)
Requires-Dist: cycler (>=0.10.0)
Requires-Dist: deprecation (==2.0.7)
Requires-Dist: joblib (>=0.13.2)
Requires-Dist: kiwisolver (>=1.1.0)
Requires-Dist: matplotlib (>=3.0.3)
Requires-Dist: numpy (>=1.17.0)
Requires-Dist: pandas (>=0.23.4)
Requires-Dist: pyparsing (>=2.4.0)
Requires-Dist: python-dateutil (>=2.8.0)
Requires-Dist: pytz (>=2019.1)
Requires-Dist: scipy (>=1.2.1)
Requires-Dist: six (>=1.12.0)
